[
  {"objeto":"laboratorio","img":"laboratorio.jpg","quantidade":11},
  {"objeto":"cadeira","img":"cadeira.jpg","quantidade":7},
  {"objeto":"mesa","img":"mesa.jpg","quantidade":4},
  {"objeto":"internet","img":"internet.jpg","quantidade":8},
  {"objeto":"livro","img":"livro.jpg","quantidade":5},
  {"objeto":"quadro","img":"quadro.jpg","quantidade":6},
  {"objeto":"caderno","img":"caderno.jpg","quantidade":7},
  {"objeto":"papel","img":"papel.jpg","quantidade":5},
  {"objeto":"ventilador","img":"ventilador.jpg","quantidade":10},
  {"objeto":"borracha","img":"borracha.jpg","quantidade":8},
  {"objeto":"corretivo","img":"corretivo.jpg","quantidade":9},
  {"objeto":"caneta","img":"caneta.jpg","quantidade":6},
  {"objeto":"mochila","img":"mochila.jpg","quantidade":7},
  {"objeto":"telefone","img":"telefone.jpg","quantidade":8},
  {"objeto":"tv","img":"tv.jpg","quantidade":2},
  {"objeto":"carro","img":"carro.jpg","quantidade":5},
  {"objeto":"biblioteca","img":"biblioteca.jpg","quantidade":10},
  {"objeto":"banheiro","img":"banheiro.jpg","quantidade":8},
  {"objeto":"secretaria","img":"secretaria.jpg","quantidade":10},
  {"objeto":"escola","img":"escola.jpg","quantidade":6},

  {"objeto":"azul","img":"azul.jpg","quantidade":4},
  {"objeto":"branco","img":"branco.jpg","quantidade":6},
  {"objeto":"marron","img":"marron.jpg","quantidade":6},
  {"objeto":"ouro","img":"ouro.jpg","quantidade":4},
  {"objeto":"prata","img":"prata.jpg","quantidade":5},
  {"objeto":"cinza","img":"cinza.png","quantidade":5},
  {"objeto":"preto","img":"preto.jpg","quantidade":5},
  {"objeto":"rosa","img":"rosa.jpg","quantidade":4},
  {"objeto":"vermelho","img":"vermelho.jpg","quantidade":8},
  {"objeto":"verde","img":"verde.jpg","quantidade":5},

  {"objeto":"cachaça","img":"cachaça.jpg","quantidade":7},
  {"objeto":"agua","img":"agua.jpg","quantidade":4},
  {"objeto":"cerveja","img":"cerveja.jpg","quantidade":7},
  {"objeto":"refrigerante","img":"refrigerante.jpg","quantidade":12},
  {"objeto":"whisky","img":"whisky.jpg","quantidade":6},
  {"objeto":"suco","img":"suco.jpg","quantidade":4},
  {"objeto":"vinho","img":"vinho.jpg","quantidade":5},

  {"objeto":"zero","img":"zero.jpg","quantidade":4},
  {"objeto":"um","img":"um.jpg","quantidade":2},
  {"objeto":"dois","img":"dois.jpg","quantidade":4},
  {"objeto":"tres","img":"tres.jpg","quantidade":4},
  {"objeto":"quatro","img":"quatro.jpg","quantidade":6},
  {"objeto":"cinco","img":"cinco.jpg","quantidade":5},
  {"objeto":"seis","img":"seis.jpg","quantidade":4},
  {"objeto":"sete","img":"sete.jpg","quantidade":4},
  {"objeto":"oito","img":"oito.jpg","quantidade":4},
  {"objeto":"nove","img":"nove.jpg","quantidade":4},

  {"objeto":"cachorro","img":"cachorro.jpg","quantidade":8},
  {"objeto":"leao","img":"leao.jpg","quantidade":4},
  {"objeto":"rato","img":"rato.jpg","quantidade":4},
  {"objeto":"cavalo","img":"cavalo.jpg","quantidade":6},
  {"objeto":"girafa","img":"girafa.jpg","quantidade":6},
  {"objeto":"sapo","img":"sapo.jpg","quantidade":4},
  {"objeto":"gato","img":"gato.jpg","quantidade":4},
  {"objeto":"tartaruga","img":"tartaruga.jpg","quantidade":9},
  {"objeto":"gaviao","img":"gaviao.jpg","quantidade":6},
  {"objeto":"zebra","img":"zebra.jpg","quantidade":5},
  {"objeto":"jacare","img":"jacare.jpg","quantidade":6},
  {"objeto":"burro","img":"burro.jpg","quantidade":5},
  {"objeto":"cobra","img":"cobra.jpg","quantidade":5},
  {"objeto":"galinha","img":"galinha.jpg","quantidade":7},

  {"objeto":"gato","img":"gato.jpg","quantidade":4},
  {"objeto":"leao","img":"leao.jpg","quantidade":4},
  {"objeto":"urso","img":"urso.jpg","quantidade":4},
  {"objeto":"lobo","img":"lobo.jpg","quantidade":4},
  {"objeto":"regua","img":"regua.jpg","quantidade":5},
  {"objeto":"agenda","img":"agenda.jpg","quantidade":6},
  {"objeto":"tesoura","img":"tesoura.png","quantidade":7},
  {"objeto":"lapis","img":"lapis.jpg","quantidade":5},
  {"objeto":"peao","img":"peao.jpg","quantidade":4},
  {"objeto":"aviao","img":"aviao.jpg","quantidade":5},
  {"objeto":"boneco","img":"boneco.jpg","quantidade":6},
  {"objeto":"patins","img":"patins.jpg","quantidade":6}
]
